wpostgresql/__init__.py
wpostgresql/wpostgresql/__init__.py
wpostgresql/wpostgresql/controller.py
wpostgresql-0.1.0.dist-info/LICENSE
wpostgresql-0.1.0.dist-info/METADATA
wpostgresql-0.1.0.dist-info/WHEEL
wpostgresql-0.1.0.dist-info/top_level.txt
wpostgresql-0.1.0.dist-info/RECORD
