Metadata-Version: 2.2
Name: wpostgresql
Version: 0.1.0
Summary: Utilities for Python in postgresql
Home-page: https://github.com/wisrovi/wpostgresql
Author: William Steve Rodriguez Villamizar
Author-email: wisrovi <wisrovi.rodriguez@gmail.com>
License: MIT License
Project-URL: Homepage, https://github.com/wisrovi/wpostgresql
Project-URL: Bug Tracker, https://github.com/wisrovi/wpostgresql/issues
Classifier: Programming Language :: Python :: 3
Classifier: License :: OSI Approved :: MIT License
Classifier: Operating System :: OS Independent
Requires-Python: >=3.6
License-File: LICENSE
Dynamic: author
Dynamic: home-page
Dynamic: requires-python
